pasec/__init__.py
pasec/pasec.py
pasec-2.0.0.dist-info/METADATA
pasec-2.0.0.dist-info/WHEEL
pasec-2.0.0.dist-info/top_level.txt
pasec-2.0.0.dist-info/RECORD
