Metadata-Version: 2.1
Name: pasec
Version: 2.0.0
Summary: A strong password Generator using weak passphrase.
Home-page: https://github.com/5uroj/pasec-py
Author: ssuroj (Suroj Sapkota)
Author-email: <surojsapkota1@gmail.com>
Keywords: Password,Security,Password Generator,PaSec
Classifier: Programming Language :: Python :: 3
Classifier: License :: OSI Approved :: MIT License
Classifier: Operating System :: OS Independent
